offlinesec_client/__init__.py
offlinesec_client/__main__.py
offlinesec_client/abap_system.py
offlinesec_client/agr_1251.py
offlinesec_client/agr_cfg_read.py
offlinesec_client/api_sec_notes.py
offlinesec_client/bo_system.py
offlinesec_client/cmd_user_input.py
offlinesec_client/config.py
offlinesec_client/const.py
offlinesec_client/cwbntcust.py
offlinesec_client/exclude_params.py
offlinesec_client/func.py
offlinesec_client/get_reports.py
offlinesec_client/java_system.py
offlinesec_client/masking.py
offlinesec_client/multi_systems.py
offlinesec_client/req_abap_review.py
offlinesec_client/req_bo_notes.py
offlinesec_client/req_java_notes.py
offlinesec_client/req_notes_report.py
offlinesec_client/req_param_report.py
offlinesec_client/req_patch_day.py
offlinesec_client/req_rfc_report.py
offlinesec_client/req_roles_report.py
offlinesec_client/req_sec_notes.py
offlinesec_client/resolve_report.py
offlinesec_client/rfc_connector.py
offlinesec_client/rfcdes.py
offlinesec_client/rsparam.py
offlinesec_client/sap_gui.py
offlinesec_client/sap_system.py
offlinesec_client/sap_table.py
offlinesec_client/sap_table_def.py
offlinesec_client/timer.py
offlinesec_client/yaml_cfg.py
offlinesec_client/yaml_cfg_read.py
offlinesec_client/yaml_cfg_rfc.py
offlinesec_client/__pycache__/__init__.cpython-312.pyc
offlinesec_client/__pycache__/masking.cpython-312.pyc
offlinesec_client/icf/__init__.py
offlinesec_client/icf/req_icf_report.py
offlinesec_client/icf/yaml_cfg_icf.py
offlinesec_client-1.1.57.dist-info/METADATA
offlinesec_client-1.1.57.dist-info/WHEEL
offlinesec_client-1.1.57.dist-info/entry_points.txt
offlinesec_client-1.1.57.dist-info/top_level.txt
offlinesec_client-1.1.57.dist-info/RECORD
