Metadata-Version: 2.1
Name: offlinesec-client
Version: 1.1.57
Summary: Offline Security Client
Home-page: https://offlinesec.com
Author: Offline Security
Author-email: info@offlinesec.com
License: UNKNOWN
Platform: UNKNOWN
Requires-Dist: requests (>=2.5.0)
Requires-Dist: openpyxl (>=3.0.0)
Requires-Dist: setuptools (~=57.0.0)
Requires-Dist: PyYAML (~=6.0.1)
Requires-Dist: editpyxl (>=0.1.10)
Requires-Dist: pysapgui (>=1.0.7) ; sys_platform == "win32"
Requires-Dist: PySapGUI (~=1.0.7) ; sys_platform == "win32"
